{
 "cells": [
  {
   "cell_type": "code",
   "execution_count": 2,
   "metadata": {},
   "outputs": [
    {
     "data": {
      "text/plain": [
       "<__main__.Object at 0x108a4d2b0>"
      ]
     },
     "execution_count": 2,
     "metadata": {},
     "output_type": "execute_result"
    }
   ],
   "source": [
    "class Object(object):\n",
    "    pass\n",
    "my_boj=Object()\n",
    "my_boj"
   ]
  },
  {
   "cell_type": "code",
   "execution_count": 7,
   "metadata": {},
   "outputs": [
    {
     "name": "stdout",
     "output_type": "stream",
     "text": [
      "  3           0 LOAD_BUILD_CLASS\n",
      "              2 LOAD_CONST               1 (<code object Object1 at 0x108a3d930, file \"<ipython-input-7-aa488a78a818>\", line 3>)\n",
      "              4 LOAD_CONST               2 ('Object1')\n",
      "              6 MAKE_FUNCTION            0\n",
      "              8 LOAD_CONST               2 ('Object1')\n",
      "             10 LOAD_GLOBAL              0 (object)\n",
      "             12 CALL_FUNCTION            3\n",
      "             14 STORE_FAST               0 (Object1)\n",
      "             16 LOAD_CONST               0 (None)\n",
      "             18 RETURN_VALUE\n"
     ]
    }
   ],
   "source": [
    "import dis\n",
    "def t():\n",
    "   class Object1(object): \n",
    "            pass \n",
    "dis.dis(t)"
   ]
  },
  {
   "cell_type": "code",
   "execution_count": 11,
   "metadata": {},
   "outputs": [
    {
     "data": {
      "text/plain": [
       "'foo'"
      ]
     },
     "execution_count": 11,
     "metadata": {},
     "output_type": "execute_result"
    }
   ],
   "source": [
    "Object.new_attr='foo'\n",
    "Object.new_attr"
   ]
  },
  {
   "cell_type": "code",
   "execution_count": 12,
   "metadata": {},
   "outputs": [
    {
     "data": {
      "text/plain": [
       "type"
      ]
     },
     "execution_count": 12,
     "metadata": {},
     "output_type": "execute_result"
    }
   ],
   "source": [
    "Object.__class__"
   ]
  },
  {
   "cell_type": "code",
   "execution_count": 13,
   "metadata": {},
   "outputs": [
    {
     "data": {
      "text/plain": [
       "type"
      ]
     },
     "execution_count": 13,
     "metadata": {},
     "output_type": "execute_result"
    }
   ],
   "source": [
    "Object.__class__.__class__"
   ]
  },
  {
   "cell_type": "code",
   "execution_count": 14,
   "metadata": {},
   "outputs": [
    {
     "data": {
      "text/plain": [
       "type"
      ]
     },
     "execution_count": 14,
     "metadata": {},
     "output_type": "execute_result"
    }
   ],
   "source": [
    "Object.__class__.__class__.__class__"
   ]
  },
  {
   "cell_type": "code",
   "execution_count": null,
   "metadata": {},
   "outputs": [],
   "source": [
    "class Foo(object):\n",
    "    __metaclass__="
   ]
  }
 ],
 "metadata": {
  "kernelspec": {
   "display_name": "Python 3",
   "language": "python",
   "name": "python3"
  },
  "language_info": {
   "codemirror_mode": {
    "name": "ipython",
    "version": 3
   },
   "file_extension": ".py",
   "mimetype": "text/x-python",
   "name": "python",
   "nbconvert_exporter": "python",
   "pygments_lexer": "ipython3",
   "version": "3.6.5"
  }
 },
 "nbformat": 4,
 "nbformat_minor": 2
}
